examples/__init__.py
examples/example_backtest.py
examples/example_strategy.py
examples/intro_example.py
quantaforge/__init__.py
quantaforge/backtest.py
quantaforge/data_feed.py
quantaforge/indicator.py
quantaforge/model.py
quantaforge/optimizer.py
quantaforge/order_execution.py
quantaforge/portfolio.py
quantaforge/position.py
quantaforge/report.py
quantaforge/risk_management.py
quantaforge/signal.py
quantaforge/strategy.py
quantaforge/utils.py
quantaforge/c_modules/__init__.py
quantaforge/cython_modules/__init__.py
tests/__init__.py
tests/test_backtest.py
tests/test_order_execution.py
tests/test_portfolio.py
tests/test_strategy.py
quantaforge-0.1.3.dist-info/LICENSE
quantaforge-0.1.3.dist-info/METADATA
quantaforge-0.1.3.dist-info/WHEEL
quantaforge-0.1.3.dist-info/top_level.txt
quantaforge-0.1.3.dist-info/RECORD
