Metadata-Version: 2.1
Name: quantaforge
Version: 0.1.3
Summary: A comprehensive library for creating and backtesting trading strategies.
Home-page: https://github.com/ndavidson19/QuantaForge
Author: Nicholas Davidson
Author-email: Nicholas Davidson <nrddodger@gmail.com>
License: MIT
Project-URL: Homepage, https://github.com/ndavidson19/QuantaForge
Classifier: Programming Language :: Python :: 3
Classifier: License :: OSI Approved :: MIT License
Classifier: Operating System :: OS Independent
Requires-Python: >=3.6
License-File: LICENSE
Requires-Dist: scikit-learn
Requires-Dist: polars
Requires-Dist: Cython
Requires-Dist: numpy
Requires-Dist: ib-insync
Requires-Dist: confluent-kafka
